{"name":"module-csv","components":[{"hidden":false,"type":"PROCESSOR","displayName":"CSV Read","fullyQualifiedName":"com.reedelk.csv.component.CSVRead","properties":[{"name":"format","example":"MONGODB_CSV","initValue":"###USE_DEFAULT_VALUE###","displayName":"CSV Format","defaultValue":"DEFAULT","type":{"classname":"com.reedelk.module.descriptor.model.TypeEnumDescriptor","instance":{"nameAndDisplayNameMap":{"EXCEL":"Excel","POSTGRESQL_TEXT":"PostgreSQL TEXT","MYSQL":"MySQL","MONGODB_CSV":"MongoDB CSV","INFORMIX_UNLOAD_CSV":"Informix Unload CSV","DEFAULT":"Default","INFORMIX_UNLOAD":"Informix Unload","ORACLE":"Oracle","POSTGRESQL_CSV":"PostgreSQL CSV","RFC4180":"RFC4180","MONGODB_TSV":"MongoDB TSV"},"type":"java.lang.Enum"}},"whens":[],"autocompleteVariables":[]},{"name":"file","initValue":"###USE_DEFAULT_VALUE###","displayName":"CSV File","type":{"classname":"com.reedelk.module.descriptor.model.TypeDynamicValueDescriptor","instance":{"type":"com.reedelk.runtime.api.script.dynamicvalue.DynamicString"}},"whens":[],"autocompleteVariables":[]},{"name":"delimiter","group":"Advanced","initValue":"###USE_DEFAULT_VALUE###","displayName":"Delimiter","type":{"classname":"com.reedelk.module.descriptor.model.TypePrimitiveDescriptor","instance":{"type":"java.lang.String"}},"whens":[],"autocompleteVariables":[]},{"name":"firstRecordAsHeader","group":"Advanced","initValue":"###USE_DEFAULT_VALUE###","displayName":"First record as header","type":{"classname":"com.reedelk.module.descriptor.model.TypePrimitiveDescriptor","instance":{"type":"java.lang.Boolean"}},"whens":[],"autocompleteVariables":[]},{"name":"allowMissingColumnNames","group":"Advanced","initValue":"###USE_DEFAULT_VALUE###","displayName":"Allow missing column names","type":{"classname":"com.reedelk.module.descriptor.model.TypePrimitiveDescriptor","instance":{"type":"java.lang.Boolean"}},"whens":[],"autocompleteVariables":[]},{"name":"allowDuplicateHeaderNames","group":"Advanced","initValue":"###USE_DEFAULT_VALUE###","displayName":"First record as header","type":{"classname":"com.reedelk.module.descriptor.model.TypePrimitiveDescriptor","instance":{"type":"java.lang.Boolean"}},"whens":[],"autocompleteVariables":[]},{"name":"trim","group":"Advanced","initValue":"###USE_DEFAULT_VALUE###","displayName":"Trim","type":{"classname":"com.reedelk.module.descriptor.model.TypePrimitiveDescriptor","instance":{"type":"java.lang.Boolean"}},"whens":[],"autocompleteVariables":[]},{"name":"ignoreEmptyLines","group":"Advanced","initValue":"###USE_DEFAULT_VALUE###","displayName":"Ignore empty lines","type":{"classname":"com.reedelk.module.descriptor.model.TypePrimitiveDescriptor","instance":{"type":"java.lang.Boolean"}},"whens":[],"autocompleteVariables":[]}]},{"hidden":false,"type":"PROCESSOR","displayName":"CSV Write","fullyQualifiedName":"com.reedelk.csv.component.CSVWrite","properties":[{"name":"headers","initValue":"###USE_DEFAULT_VALUE###","displayName":"Headers","type":{"classname":"com.reedelk.module.descriptor.model.TypeListDescriptor","instance":{"valueType":{"classname":"com.reedelk.module.descriptor.model.TypePrimitiveDescriptor","instance":{"type":"java.lang.String"}},"tabGroup":"Headers","type":"java.util.List"}},"whens":[],"autocompleteVariables":[]}]}],"autocompleteItems":[],"autocompleteTypes":[]}